kg_lokistack/__init__.py
kg_lokistack/builder.py
kg_lokistack/lokiconfigfile.py
kg_lokistack/option.py
kg_lokistack/promtailconfigfile.py
kg_lokistack/py.typed
kg_lokistack/tests/__init__.py
kg_lokistack/tests/test_builder.py
kg_lokistack-0.8.3.dist-info/LICENSE
kg_lokistack-0.8.3.dist-info/METADATA
kg_lokistack-0.8.3.dist-info/WHEEL
kg_lokistack-0.8.3.dist-info/top_level.txt
kg_lokistack-0.8.3.dist-info/RECORD
