Metadata-Version: 2.1
Name: kg-lokistack
Version: 0.8.3
Summary: KubraGen Builder: Loki Stack
Home-page: https://github.com/RangelReale/kg_lokistack
Author: Rangel Reale
Author-email: rangelreale@gmail.com
License: UNKNOWN
Platform: UNKNOWN
Classifier: Programming Language :: Python :: 3
Classifier: License :: OSI Approved :: MIT License
Classifier: Operating System :: OS Independent
Requires-Python: >=3.6
Requires-Dist: kubragen (>=0.8.4)
Requires-Dist: kg-grafana (>=0.8.4)
Requires-Dist: kg-loki (>=0.8.0)
Requires-Dist: kg-promtail (>=0.8.0)
